{
  "main": {
    "id": "b8afb9232e347619",
    "type": "split",
    "children": [
      {
        "id": "438c1a7e8461736c",
        "type": "tabs",
        "dimension": 47.2808701215611,
        "children": [
          {
            "id": "d83d1234674b7af3",
            "type": "leaf",
            "state": {
              "type": "markdown",
              "state": {
                "file": "0.0 Cyber Security Course/Notes/Week 04/20240717 - Day 017.md",
                "mode": "source",
                "source": false
              }
            }
          },
          {
            "id": "6add3915909438bc",
            "type": "leaf",
            "state": {
              "type": "markdown",
              "state": {
                "file": "5.0 Programming/5.1 Programming Languages/Python.md",
                "mode": "source",
                "source": false
              }
            }
          },
          {
            "id": "8aa59529a0e8fd65",
            "type": "leaf",
            "state": {
              "type": "markdown",
              "state": {
                "file": "0.0 Cyber Security Course/Terminologies.md",
                "mode": "source",
                "source": false
              }
            }
          }
        ],
        "currentTab": 2
      },
      {
        "id": "2fb0e64401067da2",
        "type": "tabs",
        "dimension": 52.7191298784389,
        "children": [
          {
            "id": "e0a48fc8ccbc7fd8",
            "type": "leaf",
            "state": {
              "type": "markdown",
              "state": {
                "file": "6.0 Cryptography/Cryptography.md",
                "mode": "source",
                "source": false
              }
            }
          },
          {
            "id": "4243e859685067ea",
            "type": "leaf",
            "state": {
              "type": "markdown",
              "state": {
                "file": "1.0 Types of Attacks & Defense/1.1 Attacks/1.1.1 Types of Attacks.md",
                "mode": "source",
                "source": false
              }
            }
          },
          {
            "id": "a83be39b0c62d3e8",
            "type": "leaf",
            "state": {
              "type": "markdown",
              "state": {
                "file": "0.0 Cyber Security Course/Tools.md",
                "mode": "source",
                "source": false
              }
            }
          }
        ],
        "currentTab": 2
      }
    ],
    "direction": "vertical"
  },
  "left": {
    "id": "8034c17c489e705e",
    "type": "split",
    "children": [
      {
        "id": "6ff84dafb194553f",
        "type": "tabs",
        "children": [
          {
            "id": "cba70bc0aa0f21a9",
            "type": "leaf",
            "state": {
              "type": "file-explorer",
              "state": {
                "sortOrder": "alphabetical"
              }
            }
          },
          {
            "id": "c887436978062a9d",
            "type": "leaf",
            "state": {
              "type": "search",
              "state": {
                "query": "",
                "matchingCase": false,
                "explainSearch": true,
                "collapseAll": true,
                "extraContext": true,
                "sortOrder": "alphabetical"
              }
            }
          },
          {
            "id": "58d0857643b2b8bf",
            "type": "leaf",
            "state": {
              "type": "bookmarks",
              "state": {}
            }
          }
        ]
      }
    ],
    "direction": "horizontal",
    "width": 286.5
  },
  "right": {
    "id": "ef67db9403793248",
    "type": "split",
    "children": [
      {
        "id": "28c3a1cd0676181f",
        "type": "tabs",
        "children": [
          {
            "id": "7a1fae5230a128f5",
            "type": "leaf",
            "state": {
              "type": "backlink",
              "state": {
                "file": "0.0 Cyber Security Course/Terminologies.md",
                "collapseAll": false,
                "extraContext": false,
                "sortOrder": "alphabetical",
                "showSearch": false,
                "searchQuery": "",
                "backlinkCollapsed": false,
                "unlinkedCollapsed": true
              }
            }
          },
          {
            "id": "6f1ee4f624c67e50",
            "type": "leaf",
            "state": {
              "type": "outgoing-link",
              "state": {
                "file": "0.0 Cyber Security Course/Terminologies.md",
                "linksCollapsed": false,
                "unlinkedCollapsed": true
              }
            }
          },
          {
            "id": "390d1cfbb93a7251",
            "type": "leaf",
            "state": {
              "type": "tag",
              "state": {
                "sortOrder": "frequency",
                "useHierarchy": true
              }
            }
          },
          {
            "id": "748d337d45644e7f",
            "type": "leaf",
            "state": {
              "type": "markdown",
              "state": {
                "file": "0.0 Cyber Security Course/Terminologies.md",
                "mode": "source",
                "source": false
              }
            }
          },
          {
            "id": "6bd64327369b895d",
            "type": "leaf",
            "state": {
              "type": "outline",
              "state": {
                "file": "0.0 Cyber Security Course/Terminologies.md"
              }
            }
          }
        ],
        "currentTab": 3
      }
    ],
    "direction": "horizontal",
    "width": 200,
    "collapsed": true
  },
  "left-ribbon": {
    "hiddenItems": {
      "switcher:Open quick switcher": false,
      "graph:Open graph view": false,
      "canvas:Create new canvas": false,
      "daily-notes:Open today's daily note": false,
      "templates:Insert template": false,
      "command-palette:Open command palette": false
    }
  },
  "active": "8aa59529a0e8fd65",
  "lastOpenFiles": [
    "0.0 Cyber Security Course/Tools.md",
    "0.0 Cyber Security Course/Terminologies.md",
    "0.0 Cyber Security Course/Notes/Week 04/20240717 - Day 017.md",
    "1.0 Types of Attacks & Defense/1.1 Attacks/1.1.1 Types of Attacks.md",
    "6.0 Cryptography/Cryptography.md",
    "3.0 Software/3.1 Operating Systems/3.1.1 Desktops & Laptops/3.1.1.1 Windows (10 & 11).md",
    "3.0 Software/3.1 Operating Systems/3.1.1 Desktops & Laptops/3.1.1.2 Linux & Unix.md",
    "13.0 Cloud Services/AWS.md",
    "5.0 Programming/5.1 Programming Languages/Python.md",
    "0.0 Cyber Security Course/Commands.md",
    "0.0 Cyber Security Course/Notes/MuckingAroundPage.md",
    "0.0 Cyber Security Course/Resources.md",
    "2024-07-16.md",
    "3.0 Software/3.2 Applications/Applications.md",
    "0.0 Cyber Security Course/Notes/Week 03/20240708-20240712  - Day 010-Day 14.md",
    "0.0 Cyber Security Course/Notes/Week 04/20240715 - Day 015.md",
    "0.0 Cyber Security Course/Notes/Week 02/20240705 - Day 009.md",
    "0.0 Cyber Security Course/Notes/Week 02/20240702 - Day 006.md",
    "0.0 Cyber Security Course/Notes/Week 02/20240701 - Day 005.md",
    "0.0 Cyber Security Course/Notes/Week 02/20240704 - Day 008.md",
    "Untitled.canvas",
    "0.0 Cyber Security Course/Notes/Week 01/20240624 - Day 001.md",
    "2.0 Hardware/2.4 Servers/2.4.1 Web Servers/Web Servers.md",
    "6.0 Cryptography/Base64.md",
    "9.0 Virtual Machines/Virtual Machines (VM's).md",
    "0.0 Cyber Security Course/Notes/Week 04/20240716 - Day 016.md",
    "0.0 Cyber Security Course/Cyber Security Course.md",
    "4.0 Networking/Web Browsers",
    "2.0 Hardware/2.4 Servers/2.4.1 Web Servers",
    "2.0 Hardware/2.4 Servers",
    "0.0 Cyber Security Course/Notes/Week 04",
    "Week",
    "0.0 Cyber Security Course/Notes/Week 03",
    "Untitled 1.canvas",
    "5.0 Programming/5.1 Programming Languages",
    "13.0 Cloud Services",
    "3.0 Software/3.2 Applications",
    "12.0 Artificial Intelligence",
    "99.99 Images Used/TutorialsPointProcThrComparison.png",
    "99.99 Images Used/Reddit_csharp_HandlesDef.png",
    "99.99 Images Used/Clones_20240702.png",
    "99.99 Images Used/Pasted image 20240702214553.png",
    "Pasted image 20240702104549.png",
    "Pasted image 20240625173221.png"
  ]
}